<?xml version="1.0" encoding="UTF-8"?>
<!DOCTYPE mapper PUBLIC "-//mybatis.org//DTD Mapper 3.0//EN" "http://mybatis.org/dtd/mybatis-3-mapper.dtd">
<mapper namespace="com.database.dao.WordResourceMapper">
  <resultMap id="BaseResultMap" type="com.database.bean.WordResource">
    <!--
      WARNING - @mbggenerated
      This element is automatically generated by MyBatis Generator, do not modify.
      This element was generated on Fri Dec 18 15:37:48 GMT+08:00 2015.
    -->
    <id column="resource_id" jdbcType="INTEGER" property="resourceId" />
    <result column="user_id" jdbcType="INTEGER" property="userId" />
    <result column="resource_type" jdbcType="CHAR" property="resourceType" />
    <result column="buy_type" jdbcType="CHAR" property="buyType" />
    <result column="journal_id" jdbcType="INTEGER" property="journalId" />
    <result column="article_id" jdbcType="INTEGER" property="articleId" />
    <result column="price" jdbcType="DOUBLE" property="price" />
    <result column="cart_id" jdbcType="INTEGER" property="cartId" />
    <result column="do_id" jdbcType="INTEGER" property="doId" />
    <result column="start_time" jdbcType="TIMESTAMP" property="startTime" />
    <result column="end_time" jdbcType="TIMESTAMP" property="endTime" />
    <result column="create_time" jdbcType="TIMESTAMP" property="createTime" />
  </resultMap>
  <sql id="Example_Where_Clause">
    <!--
      WARNING - @mbggenerated
      This element is automatically generated by MyBatis Generator, do not modify.
      This element was generated on Fri Dec 18 15:37:48 GMT+08:00 2015.
    -->
    <where>
      <foreach collection="oredCriteria" item="criteria" separator="or">
        <if test="criteria.valid">
          <trim prefix="(" prefixOverrides="and" suffix=")">
            <foreach collection="criteria.criteria" item="criterion">
              <choose>
                <when test="criterion.noValue">
                  and ${criterion.condition}
                </when>
                <when test="criterion.singleValue">
                  and ${criterion.condition} #{criterion.value}
                </when>
                <when test="criterion.betweenValue">
                  and ${criterion.condition} #{criterion.value} and #{criterion.secondValue}
                </when>
                <when test="criterion.listValue">
                  and ${criterion.condition}
                  <foreach close=")" collection="criterion.value" item="listItem" open="(" separator=",">
                    #{listItem}
                  </foreach>
                </when>
              </choose>
            </foreach>
          </trim>
        </if>
      </foreach>
    </where>
  </sql>
  <sql id="Update_By_Example_Where_Clause">
    <!--
      WARNING - @mbggenerated
      This element is automatically generated by MyBatis Generator, do not modify.
      This element was generated on Fri Dec 18 15:37:48 GMT+08:00 2015.
    -->
    <where>
      <foreach collection="example.oredCriteria" item="criteria" separator="or">
        <if test="criteria.valid">
          <trim prefix="(" prefixOverrides="and" suffix=")">
            <foreach collection="criteria.criteria" item="criterion">
              <choose>
                <when test="criterion.noValue">
                  and ${criterion.condition}
                </when>
                <when test="criterion.singleValue">
                  and ${criterion.condition} #{criterion.value}
                </when>
                <when test="criterion.betweenValue">
                  and ${criterion.condition} #{criterion.value} and #{criterion.secondValue}
                </when>
                <when test="criterion.listValue">
                  and ${criterion.condition}
                  <foreach close=")" collection="criterion.value" item="listItem" open="(" separator=",">
                    #{listItem}
                  </foreach>
                </when>
              </choose>
            </foreach>
          </trim>
        </if>
      </foreach>
    </where>
  </sql>
  <sql id="Base_Column_List">
    <!--
      WARNING - @mbggenerated
      This element is automatically generated by MyBatis Generator, do not modify.
      This element was generated on Fri Dec 18 15:37:48 GMT+08:00 2015.
    -->
    resource_id, user_id, resource_type, buy_type, journal_id, article_id, price, cart_id, 
    do_id, start_time, end_time, create_time
  </sql>
  <select id="selectByExample" parameterType="com.database.bean.WordResourceExample" resultMap="BaseResultMap">
    <!--
      WARNING - @mbggenerated
      This element is automatically generated by MyBatis Generator, do not modify.
      This element was generated on Fri Dec 18 15:37:48 GMT+08:00 2015.
    -->
    select
    <if test="distinct">
      distinct
    </if>
    <include refid="Base_Column_List" />
    from word_resource
    <if test="_parameter != null">
      <include refid="Example_Where_Clause" />
    </if>
    <if test="orderByClause != null">
      order by ${orderByClause}
    </if>
    <if test="limitStart != null and limitStart&gt;=0">
      limit #{limitStart} , #{limitEnd}
    </if>
  </select>
  <select id="selectByPrimaryKey" parameterType="java.lang.Integer" resultMap="BaseResultMap">
    <!--
      WARNING - @mbggenerated
      This element is automatically generated by MyBatis Generator, do not modify.
      This element was generated on Fri Dec 18 15:37:48 GMT+08:00 2015.
    -->
    select 
    <include refid="Base_Column_List" />
    from word_resource
    where resource_id = #{resourceId,jdbcType=INTEGER}
  </select>
  <delete id="deleteByPrimaryKey" parameterType="java.lang.Integer">
    <!--
      WARNING - @mbggenerated
      This element is automatically generated by MyBatis Generator, do not modify.
      This element was generated on Fri Dec 18 15:37:48 GMT+08:00 2015.
    -->
    delete from word_resource
    where resource_id = #{resourceId,jdbcType=INTEGER}
  </delete>
  <delete id="deleteByExample" parameterType="com.database.bean.WordResourceExample">
    <!--
      WARNING - @mbggenerated
      This element is automatically generated by MyBatis Generator, do not modify.
      This element was generated on Fri Dec 18 15:37:48 GMT+08:00 2015.
    -->
    delete from word_resource
    <if test="_parameter != null">
      <include refid="Example_Where_Clause" />
    </if>
  </delete>
  <insert id="insert" parameterType="com.database.bean.WordResource">
    <!--
      WARNING - @mbggenerated
      This element is automatically generated by MyBatis Generator, do not modify.
      This element was generated on Fri Dec 18 15:37:48 GMT+08:00 2015.
    -->
    insert into word_resource (resource_id, user_id, resource_type, 
      buy_type, journal_id, article_id, 
      price, cart_id, do_id, 
      start_time, end_time, create_time
      )
    values (#{resourceId,jdbcType=INTEGER}, #{userId,jdbcType=INTEGER}, #{resourceType,jdbcType=CHAR}, 
      #{buyType,jdbcType=CHAR}, #{journalId,jdbcType=INTEGER}, #{articleId,jdbcType=INTEGER}, 
      #{price,jdbcType=DOUBLE}, #{cartId,jdbcType=INTEGER}, #{doId,jdbcType=INTEGER}, 
      #{startTime,jdbcType=TIMESTAMP}, #{endTime,jdbcType=TIMESTAMP}, #{createTime,jdbcType=TIMESTAMP}
      )
  </insert>
  <insert id="insertSelective" parameterType="com.database.bean.WordResource" useGeneratedKeys="true" keyProperty="resourceId">
    <!--
      WARNING - @mbggenerated
      This element is automatically generated by MyBatis Generator, do not modify.
      This element was generated on Fri Dec 18 15:37:48 GMT+08:00 2015.
    -->
    insert into word_resource
    <trim prefix="(" suffix=")" suffixOverrides=",">
      <if test="resourceId != null">
        resource_id,
      </if>
      <if test="userId != null">
        user_id,
      </if>
      <if test="resourceType != null">
        resource_type,
      </if>
      <if test="buyType != null">
        buy_type,
      </if>
      <if test="journalId != null">
        journal_id,
      </if>
      <if test="articleId != null">
        article_id,
      </if>
      <if test="price != null">
        price,
      </if>
      <if test="cartId != null">
        cart_id,
      </if>
      <if test="doId != null">
        do_id,
      </if>
      <if test="startTime != null">
        start_time,
      </if>
      <if test="endTime != null">
        end_time,
      </if>
      <if test="createTime != null">
        create_time,
      </if>
    </trim>
    <trim prefix="values (" suffix=")" suffixOverrides=",">
      <if test="resourceId != null">
        #{resourceId,jdbcType=INTEGER},
      </if>
      <if test="userId != null">
        #{userId,jdbcType=INTEGER},
      </if>
      <if test="resourceType != null">
        #{resourceType,jdbcType=CHAR},
      </if>
      <if test="buyType != null">
        #{buyType,jdbcType=CHAR},
      </if>
      <if test="journalId != null">
        #{journalId,jdbcType=INTEGER},
      </if>
      <if test="articleId != null">
        #{articleId,jdbcType=INTEGER},
      </if>
      <if test="price != null">
        #{price,jdbcType=DOUBLE},
      </if>
      <if test="cartId != null">
        #{cartId,jdbcType=INTEGER},
      </if>
      <if test="doId != null">
        #{doId,jdbcType=INTEGER},
      </if>
      <if test="startTime != null">
        #{startTime,jdbcType=TIMESTAMP},
      </if>
      <if test="endTime != null">
        #{endTime,jdbcType=TIMESTAMP},
      </if>
      <if test="createTime != null">
        #{createTime,jdbcType=TIMESTAMP},
      </if>
    </trim>
  </insert>
  <select id="countByExample" parameterType="com.database.bean.WordResourceExample" resultType="java.lang.Integer">
    <!--
      WARNING - @mbggenerated
      This element is automatically generated by MyBatis Generator, do not modify.
      This element was generated on Fri Dec 18 15:37:48 GMT+08:00 2015.
    -->
    select count(*) from word_resource
    <if test="_parameter != null">
      <include refid="Example_Where_Clause" />
    </if>
  </select>
  <update id="updateByExampleSelective" parameterType="map">
    <!--
      WARNING - @mbggenerated
      This element is automatically generated by MyBatis Generator, do not modify.
      This element was generated on Fri Dec 18 15:37:48 GMT+08:00 2015.
    -->
    update word_resource
    <set>
      <if test="record.resourceId != null">
        resource_id = #{record.resourceId,jdbcType=INTEGER},
      </if>
      <if test="record.userId != null">
        user_id = #{record.userId,jdbcType=INTEGER},
      </if>
      <if test="record.resourceType != null">
        resource_type = #{record.resourceType,jdbcType=CHAR},
      </if>
      <if test="record.buyType != null">
        buy_type = #{record.buyType,jdbcType=CHAR},
      </if>
      <if test="record.journalId != null">
        journal_id = #{record.journalId,jdbcType=INTEGER},
      </if>
      <if test="record.articleId != null">
        article_id = #{record.articleId,jdbcType=INTEGER},
      </if>
      <if test="record.price != null">
        price = #{record.price,jdbcType=DOUBLE},
      </if>
      <if test="record.cartId != null">
        cart_id = #{record.cartId,jdbcType=INTEGER},
      </if>
      <if test="record.doId != null">
        do_id = #{record.doId,jdbcType=INTEGER},
      </if>
      <if test="record.startTime != null">
        start_time = #{record.startTime,jdbcType=TIMESTAMP},
      </if>
      <if test="record.endTime != null">
        end_time = #{record.endTime,jdbcType=TIMESTAMP},
      </if>
      <if test="record.createTime != null">
        create_time = #{record.createTime,jdbcType=TIMESTAMP},
      </if>
    </set>
    <if test="_parameter != null">
      <include refid="Update_By_Example_Where_Clause" />
    </if>
  </update>
  <update id="updateByExample" parameterType="map">
    <!--
      WARNING - @mbggenerated
      This element is automatically generated by MyBatis Generator, do not modify.
      This element was generated on Fri Dec 18 15:37:48 GMT+08:00 2015.
    -->
    update word_resource
    set resource_id = #{record.resourceId,jdbcType=INTEGER},
      user_id = #{record.userId,jdbcType=INTEGER},
      resource_type = #{record.resourceType,jdbcType=CHAR},
      buy_type = #{record.buyType,jdbcType=CHAR},
      journal_id = #{record.journalId,jdbcType=INTEGER},
      article_id = #{record.articleId,jdbcType=INTEGER},
      price = #{record.price,jdbcType=DOUBLE},
      cart_id = #{record.cartId,jdbcType=INTEGER},
      do_id = #{record.doId,jdbcType=INTEGER},
      start_time = #{record.startTime,jdbcType=TIMESTAMP},
      end_time = #{record.endTime,jdbcType=TIMESTAMP},
      create_time = #{record.createTime,jdbcType=TIMESTAMP}
    <if test="_parameter != null">
      <include refid="Update_By_Example_Where_Clause" />
    </if>
  </update>
  <update id="updateByPrimaryKeySelective" parameterType="com.database.bean.WordResource">
    <!--
      WARNING - @mbggenerated
      This element is automatically generated by MyBatis Generator, do not modify.
      This element was generated on Fri Dec 18 15:37:48 GMT+08:00 2015.
    -->
    update word_resource
    <set>
      <if test="userId != null">
        user_id = #{userId,jdbcType=INTEGER},
      </if>
      <if test="resourceType != null">
        resource_type = #{resourceType,jdbcType=CHAR},
      </if>
      <if test="buyType != null">
        buy_type = #{buyType,jdbcType=CHAR},
      </if>
      <if test="journalId != null">
        journal_id = #{journalId,jdbcType=INTEGER},
      </if>
      <if test="articleId != null">
        article_id = #{articleId,jdbcType=INTEGER},
      </if>
      <if test="price != null">
        price = #{price,jdbcType=DOUBLE},
      </if>
      <if test="cartId != null">
        cart_id = #{cartId,jdbcType=INTEGER},
      </if>
      <if test="doId != null">
        do_id = #{doId,jdbcType=INTEGER},
      </if>
      <if test="startTime != null">
        start_time = #{startTime,jdbcType=TIMESTAMP},
      </if>
      <if test="endTime != null">
        end_time = #{endTime,jdbcType=TIMESTAMP},
      </if>
      <if test="createTime != null">
        create_time = #{createTime,jdbcType=TIMESTAMP},
      </if>
    </set>
    where resource_id = #{resourceId,jdbcType=INTEGER}
  </update>
  <update id="updateByPrimaryKey" parameterType="com.database.bean.WordResource">
    <!--
      WARNING - @mbggenerated
      This element is automatically generated by MyBatis Generator, do not modify.
      This element was generated on Fri Dec 18 15:37:48 GMT+08:00 2015.
    -->
    update word_resource
    set user_id = #{userId,jdbcType=INTEGER},
      resource_type = #{resourceType,jdbcType=CHAR},
      buy_type = #{buyType,jdbcType=CHAR},
      journal_id = #{journalId,jdbcType=INTEGER},
      article_id = #{articleId,jdbcType=INTEGER},
      price = #{price,jdbcType=DOUBLE},
      cart_id = #{cartId,jdbcType=INTEGER},
      do_id = #{doId,jdbcType=INTEGER},
      start_time = #{startTime,jdbcType=TIMESTAMP},
      end_time = #{endTime,jdbcType=TIMESTAMP},
      create_time = #{createTime,jdbcType=TIMESTAMP}
    where resource_id = #{resourceId,jdbcType=INTEGER}
  </update>
</mapper>